gcp_mysql/__init__.py
gcp_mysql/service.py
gcp_mysql/_internal/index_creation.py
gcp_mysql/_internal/table_creation.py
gcp_mysql/_setup/infra/local/__init__.py
gcp_mysql/_setup/infra/local/build.example.txt
gcp_mysql/_setup/infra/local/cloud-sql.json
gcp_mysql/_setup/infra/local/run-cloud-sql-proxy.sh
gcp_mysql/_setup/infra/local/docker/docker-compose.yml
gcp_mysql/utils/__init__.py
gcp_mysql/utils/factory.py
gcp_mysql/utils/query_operations.py
gcp_mysql-0.1.19.dist-info/licenses/LICENSE
gcp_mysql-0.1.19.dist-info/METADATA
gcp_mysql-0.1.19.dist-info/WHEEL
gcp_mysql-0.1.19.dist-info/top_level.txt
gcp_mysql-0.1.19.dist-info/RECORD
