Metadata-Version: 2.4
Name: gcp-mysql
Version: 0.1.19
Summary: A lightweight MySQL service wrapper for GCP environments
Author-email: Vince Berry <vince@keenai.io>
License: MIT License
Keywords: mysql,gcp,cloud-sql,pymysql,database
Classifier: Development Status :: 3 - Alpha
Classifier: Intended Audience :: Developers
Classifier: License :: OSI Approved :: MIT License
Classifier: Programming Language :: Python :: 3
Classifier: Programming Language :: Python :: 3.9
Classifier: Programming Language :: Python :: 3.10
Classifier: Programming Language :: Python :: 3.11
Classifier: Programming Language :: Python :: 3.12
Classifier: Programming Language :: Python :: 3 :: Only
Classifier: Topic :: Database
Classifier: Topic :: Software Development :: Libraries
Requires-Python: >=3.9
License-File: LICENSE
Requires-Dist: pydantic
Requires-Dist: pymysql
Requires-Dist: google-cloud-secret-manager
Provides-Extra: dev
Requires-Dist: build; extra == "dev"
Requires-Dist: twine; extra == "dev"
Dynamic: license-file
